db_talk/__index__.py
db_talk/agent.py
db_talk/async_db.py
db_talk/db.py
db_talk/execution.py
db_talk/metadata.py
talk_db-0.0.1.dist-info/METADATA
talk_db-0.0.1.dist-info/WHEEL
talk_db-0.0.1.dist-info/licenses/LICENSE
talk_db-0.0.1.dist-info/RECORD
