Metadata-Version: 2.4
Name: talk-db
Version: 0.0.1
Summary: Natural language to SQL query interface
Project-URL: Homepage, https://github.com/Nayjest/db-talk
Project-URL: Repository, https://github.com/Nayjest/db-talk
Project-URL: Issues, https://github.com/Nayjest/db-talk/issues
Author-email: Vitalii Stepanenko <mail@vitalii.in>
License-Expression: MIT
License-File: LICENSE
Keywords: database,natural-language,nlp,query,sql
Classifier: Development Status :: 3 - Alpha
Classifier: Intended Audience :: Developers
Classifier: License :: OSI Approved :: MIT License
Classifier: Programming Language :: Python :: 3
Classifier: Programming Language :: Python :: 3.10
Classifier: Programming Language :: Python :: 3.11
Classifier: Programming Language :: Python :: 3.12
Classifier: Topic :: Database
Classifier: Topic :: Software Development :: Libraries :: Python Modules
Requires-Python: >=3.10
Provides-Extra: dev
Requires-Dist: mypy>=1.11.0; extra == 'dev'
Requires-Dist: pytest>=8.0.0; extra == 'dev'
Requires-Dist: ruff>=0.8.0; extra == 'dev'
